espiownage/None.py
espiownage/__init__.py
espiownage/_nbdev.py
espiownage/core.py
espiownage/ellipse_editor.py
espiownage/gen_bboxes.py
espiownage/gen_crops.py
espiownage/gen_fake.py
espiownage/gen_masks.py
espiownage/grab_recent.py
espiownage/index.py
espiownage/scripts.py
espiownage-0.1.0.dist-info/LICENSE
espiownage-0.1.0.dist-info/METADATA
espiownage-0.1.0.dist-info/WHEEL
espiownage-0.1.0.dist-info/entry_points.txt
espiownage-0.1.0.dist-info/top_level.txt
espiownage-0.1.0.dist-info/RECORD
