Metadata-Version: 2.1
Name: espiownage
Version: 0.1.0
Summary: Ownage of ESPI image inference
Home-page: https://github.com/drscotthawley/espiownage/tree/master/
Author: Scott H. Hawley
Author-email: scott.hawley@belmont.edu
License: Apache Software License 2.0
Keywords: some keywords
Platform: UNKNOWN
Classifier: Development Status :: 3 - Alpha
Classifier: Intended Audience :: Developers
Classifier: Natural Language :: English
Classifier: Programming Language :: Python :: 3.6
Classifier: Programming Language :: Python :: 3.7
Classifier: Programming Language :: Python :: 3.8
Classifier: License :: OSI Approved :: Apache Software License
Requires-Python: >=3.6
Requires-Dist: fastai
Requires-Dist: fastcore
Requires-Dist: matplotlib
Requires-Dist: nbverbose
Requires-Dist: numpy
Requires-Dist: opencv-python
Requires-Dist: packaging
Requires-Dist: pandas
Requires-Dist: pillow (==8.2)
Requires-Dist: pip
Requires-Dist: tk
Requires-Dist: torch
Requires-Dist: wheel
Provides-Extra: dev
